Metadata-Version: 2.1
Name: bwrc-discovery-server
Version: 0.0.2
Summary: BWRC AMS ML Discovery Server
Home-page: https://github.com/BWRC-AMS-ML-Discovery
Author: The Regents of the University of California
Author-email: whh.bear@berkeley.edu
Requires-Python: >=3.7, <4
Provides-Extra: dev
